gethash/__init__.py
gethash/__main__.py
gethash/core.py
gethash/hasher.py
gethash/py.typed
gethash/script.py
gethash/backends/__init__.py
gethash/backends/hashlib.py
gethash/backends/pycryptodome.py
gethash/backends/wrappers.py
gethash/cli/__init__.py
gethash/cli/_codegen.py
gethash/cli/blake2b.py
gethash/cli/blake2s.py
gethash/cli/crc32.py
gethash/cli/md5.py
gethash/cli/sha1.py
gethash/cli/sha256.py
gethash/cli/sha3_256.py
gethash/cli/sha3_512.py
gethash/cli/sha512.py
gethash/utils/__init__.py
gethash/utils/click.py
gethash/utils/glob.py
gethash/utils/strxor.py
gethash/wrappers/__init__.py
gethash/wrappers/crc32.py
gethash-6.1.dist-info/METADATA
gethash-6.1.dist-info/WHEEL
gethash-6.1.dist-info/entry_points.txt
gethash-6.1.dist-info/licenses/LICENSE
gethash-6.1.dist-info/RECORD
