Metadata-Version: 2.1
Name: gethash
Version: 6.1
Summary: Command-line hash utility
Project-URL: Changelog, https://github.com/xymy/gethash/blob/main/CHANGELOG.md
Project-URL: Documentation, https://github.com/xymy/gethash/tree/main/docs
Project-URL: Source, https://github.com/xymy/gethash
Project-URL: Tracker, https://github.com/xymy/gethash/issues
Author-email: xymy <thyfan@163.com>
License-Expression: MIT
License-File: LICENSE
Keywords: cryptography,hash,utility
Classifier: Development Status :: 5 - Production/Stable
Classifier: Environment :: Console
Classifier: Intended Audience :: Developers
Classifier: License :: OSI Approved :: MIT License
Classifier: Operating System :: OS Independent
Classifier: Programming Language :: Python
Classifier: Programming Language :: Python :: 3
Classifier: Programming Language :: Python :: 3.9
Classifier: Programming Language :: Python :: 3.10
Classifier: Programming Language :: Python :: 3.11
Classifier: Programming Language :: Python :: 3.12
Classifier: Topic :: Security
Classifier: Topic :: Security :: Cryptography
Classifier: Topic :: Utilities
Requires-Python: >=3.9
Requires-Dist: click-didyoumean>=0.3
Requires-Dist: click-option-group>=0.5
Requires-Dist: click>=8.1
Requires-Dist: importlib-metadata>=4.10
Requires-Dist: natsort>=8.4
Requires-Dist: tqdm>=4.66
Requires-Dist: typing-extensions>=4.4
Provides-Extra: all
Requires-Dist: pycryptodome>=3.16; extra == 'all'
Provides-Extra: docs
Requires-Dist: furo>=2023.9; extra == 'docs'
Requires-Dist: myst-parser>=2.0; extra == 'docs'
Requires-Dist: rich; extra == 'docs'
Requires-Dist: sphinx-copybutton>=0.5; extra == 'docs'
Requires-Dist: sphinx>=7.2; extra == 'docs'
Provides-Extra: lint
Requires-Dist: black>=23.11; extra == 'lint'
Requires-Dist: mypy>=1.7; extra == 'lint'
Requires-Dist: ruff>=0.1.6; extra == 'lint'
Provides-Extra: test
Requires-Dist: coverage>=7.3; extra == 'test'
Requires-Dist: hypothesis>=6.86; extra == 'test'
Requires-Dist: more-itertools>=10.0; extra == 'test'
Requires-Dist: pytest-cov>=4.1; extra == 'test'
Requires-Dist: pytest>=7.4; extra == 'test'
